prms.c
prms.pyx
setup.py
ik1.egg-info/PKG-INFO
ik1.egg-info/SOURCES.txt
ik1.egg-info/dependency_links.txt
ik1.egg-info/requires.txt
ik1.egg-info/top_level.txt