Metadata-Version: 1.0
Name: ik1
Version: 0.1.2
Summary: iks test #1 package
Home-page: http://google.com
Author: ik
Author-email: pedro@gmail.com
License: MIT
Platform: UNKNOWN
